{"4228": {"test": {"17": {"movie_id": 805, "timestamp": 965312923, "Genre": "Drama", "movie_name": "Time to Kill, A (1996)", "rating": 4}, "18": {"movie_id": 2706, "timestamp": 965313318, "Genre": "Comedy", "movie_name": "American Pie (1999)", "rating": 3}, "19": {"movie_id": 225, "timestamp": 965313293, "Genre": "Drama|Thriller", "movie_name": "Disclosure (1994)", "rating": 4}, "20": {"movie_id": 3007, "timestamp": 965313093, "Genre": "Documentary", "movie_name": "American Movie (1999)", "rating": 3}, "21": {"movie_id": 102, "timestamp": 965313022, "Genre": "Comedy", "movie_name": "Mr. Wrong (1996)", "rating": 1}, "22": {"movie_id": 1121, "timestamp": 965313622, "Genre": "Drama", "movie_name": "Glory Daze (1996)", "rating": 1}}, "train": {"0": {"movie_id": 1193, "timestamp": 965313519, "Genre": "Drama", "movie_name": "One Flew Over the Cuckoo's Nest (1975)", "rating": 4}, "1": {"movie_id": 527, "timestamp": 965313465, "Genre": "Drama|War", "movie_name": "Schindler's List (1993)", "rating": 4}, "2": {"movie_id": 1721, "timestamp": 965312852, "Genre": "Drama|Romance", "movie_name": "Titanic (1997)", "rating": 4}, "3": {"movie_id": 150, "timestamp": 965313552, "Genre": "Drama", "movie_name": "Apollo 13 (1995)", "rating": 5}, "4": {"movie_id": 2028, "timestamp": 965313519, "Genre": "Action|Drama|War", "movie_name": "Saving Private Ryan (1998)", "rating": 5}, "5": {"movie_id": 3147, "timestamp": 965313180, "Genre": "Drama|Thriller", "movie_name": "Green Mile, The (1999)", "rating": 4}, "6": {"movie_id": 589, "timestamp": 965313248, "Genre": "Action|Sci-Fi|Thriller", "movie_name": "Terminator 2: Judgment Day (1991)", "rating": 5}, "7": {"movie_id": 2858, "timestamp": 965313217, "Genre": "Comedy|Drama", "movie_name": "American Beauty (1999)", "rating": 2}, "8": {"movie_id": 593, "timestamp": 965313576, "Genre": "Drama|Thriller", "movie_name": "Silence of the Lambs, The (1991)", "rating": 4}, "9": {"movie_id": 2501, "timestamp": 965313042, "Genre": "Drama", "movie_name": "October Sky (1999)", "rating": 5}, "10": {"movie_id": 318, "timestamp": 965313488, "Genre": "Drama", "movie_name": "Shawshank Redemption, The (1994)", "rating": 5}, "11": {"movie_id": 3421, "timestamp": 965313519, "Genre": "Comedy", "movie_name": "Animal House (1978)", "rating": 4}, "12": {"movie_id": 1036, "timestamp": 965313563, "Genre": "Action|Thriller", "movie_name": "Die Hard (1988)", "rating": 5}, "13": {"movie_id": 1240, "timestamp": 965313248, "Genre": "Action|Sci-Fi|Thriller", "movie_name": "Terminator, The (1984)", "rating": 5}, "14": {"movie_id": 296, "timestamp": 965313155, "Genre": "Crime|Drama", "movie_name": "Pulp Fiction (1994)", "rating": 2}, "15": {"movie_id": 1617, "timestamp": 965313552, "Genre": "Crime|Film-Noir|Mystery|Thriller", "movie_name": "L.A. Confidential (1997)", "rating": 4}, "16": {"movie_id": 223, "timestamp": 965313273, "Genre": "Comedy", "movie_name": "Clerks (1994)", "rating": 1}}}}