{"3080": {"test": {"512": {"movie_id": 417, "timestamp": 969810025, "Genre": "Comedy|Romance", "movie_name": "Barcelona (1994)", "rating": 3}, "513": {"movie_id": 1260, "timestamp": 976302319, "Genre": "Crime|Film-Noir|Thriller", "movie_name": "M (1931)", "rating": 5}, "514": {"movie_id": 2924, "timestamp": 969812032, "Genre": "Action|Comedy", "movie_name": "Drunken Master (Zui quan) (1979)", "rating": 5}, "515": {"movie_id": 2861, "timestamp": 969810525, "Genre": "Comedy|Drama", "movie_name": "For Love of the Game (1999)", "rating": 1}, "516": {"movie_id": 3859, "timestamp": 1008794761, "Genre": "Documentary", "movie_name": "Eyes of Tammy Faye, The (2000)", "rating": 4}, "517": {"movie_id": 373, "timestamp": 969811132, "Genre": "Thriller", "movie_name": "Red Rock West (1992)", "rating": 4}, "518": {"movie_id": 2073, "timestamp": 1015018915, "Genre": "Comedy", "movie_name": "Fandango (1985)", "rating": 2}, "519": {"movie_id": 2203, "timestamp": 976302319, "Genre": "Film-Noir|Thriller", "movie_name": "Shadow of a Doubt (1943)", "rating": 4}, "520": {"movie_id": 1824, "timestamp": 969809357, "Genre": "Comedy|Thriller", "movie_name": "Homegrown (1998)", "rating": 3}, "521": {"movie_id": 71, "timestamp": 976307476, "Genre": "Action", "movie_name": "Fair Game (1995)", "rating": 2}, "522": {"movie_id": 3915, "timestamp": 1018716413, "Genre": "Drama", "movie_name": "Girlfight (2000)", "rating": 4}, "523": {"movie_id": 101, "timestamp": 969811301, "Genre": "Comedy", "movie_name": "Bottle Rocket (1996)", "rating": 5}, "524": {"movie_id": 1855, "timestamp": 1015019416, "Genre": "Comedy", "movie_name": "Krippendorf's Tribe (1998)", "rating": 1}, "525": {"movie_id": 574, "timestamp": 969811583, "Genre": "Comedy|Drama", "movie_name": "Spanking the Monkey (1994)", "rating": 4}, "526": {"movie_id": 1354, "timestamp": 969811381, "Genre": "Drama", "movie_name": "Breaking the Waves (1996)", "rating": 2}, "527": {"movie_id": 306, "timestamp": 976306436, "Genre": "Drama", "movie_name": "Three Colors: Red (1994)", "rating": 4}, "528": {"movie_id": 3819, "timestamp": 969812158, "Genre": "Comedy", "movie_name": "Tampopo (1986)", "rating": 5}, "529": {"movie_id": 535, "timestamp": 969811155, "Genre": "Drama", "movie_name": "Short Cuts (1993)", "rating": 4}, "530": {"movie_id": 1194, "timestamp": 969812542, "Genre": "Comedy", "movie_name": "Up in Smoke (1978)", "rating": 4}, "531": {"movie_id": 2859, "timestamp": 1011373670, "Genre": "Documentary", "movie_name": "Stop Making Sense (1984)", "rating": 5}, "532": {"movie_id": 3903, "timestamp": 1015016259, "Genre": "Drama", "movie_name": "Urbania (2000)", "rating": 2}, "533": {"movie_id": 68, "timestamp": 969811237, "Genre": "Comedy|Romance", "movie_name": "French Twist (Gazon maudit) (1995)", "rating": 2}, "534": {"movie_id": 3823, "timestamp": 1015016284, "Genre": "Drama", "movie_name": "Wonderland (1999)", "rating": 2}, "535": {"movie_id": 1236, "timestamp": 969810038, "Genre": "Comedy|Drama", "movie_name": "Trust (1990)", "rating": 5}, "536": {"movie_id": 2330, "timestamp": 976307898, "Genre": "Documentary", "movie_name": "Hands on a Hard Body (1996)", "rating": 3}, "537": {"movie_id": 3235, "timestamp": 1015019431, "Genre": "Comedy", "movie_name": "Where the Buffalo Roam (1980)", "rating": 3}, "538": {"movie_id": 99, "timestamp": 969810912, "Genre": "Documentary", "movie_name": "Heidi Fleiss: Hollywood Madam (1995)", "rating": 4}, "539": {"movie_id": 1044, "timestamp": 969811564, "Genre": "Drama", "movie_name": "Surviving Picasso (1996)", "rating": 3}, "540": {"movie_id": 1503, "timestamp": 1015019135, "Genre": "Comedy", "movie_name": "8 Heads in a Duffel Bag (1997)", "rating": 1}, "541": {"movie_id": 1857, "timestamp": 1015018915, "Genre": "Comedy", "movie_name": "Real Blonde, The (1997)", "rating": 1}, "542": {"movie_id": 444, "timestamp": 969810422, "Genre": "Comedy|Romance", "movie_name": "Even Cowgirls Get the Blues (1993)", "rating": 1}, "543": {"movie_id": 537, "timestamp": 969810484, "Genre": "Comedy|Drama", "movie_name": "Sirens (1994)", "rating": 3}, "544": {"movie_id": 3851, "timestamp": 1044313668, "Genre": "Comedy", "movie_name": "I'm the One That I Want (2000)", "rating": 4}, "545": {"movie_id": 3544, "timestamp": 969810025, "Genre": "Comedy", "movie_name": "Shakes the Clown (1991)", "rating": 4}, "546": {"movie_id": 1163, "timestamp": 1015016213, "Genre": "Drama", "movie_name": "Mina Tannenbaum (1994)", "rating": 2}, "547": {"movie_id": 1351, "timestamp": 976307816, "Genre": "Drama", "movie_name": "Blood & Wine (1997)", "rating": 3}, "548": {"movie_id": 347, "timestamp": 969811401, "Genre": "Drama", "movie_name": "Bitter Moon (1992)", "rating": 3}, "549": {"movie_id": 2164, "timestamp": 976307746, "Genre": "Drama", "movie_name": "Surf Nazis Must Die (1987)", "rating": 2}, "550": {"movie_id": 2608, "timestamp": 976303707, "Genre": "Thriller", "movie_name": "Heaven (1998)", "rating": 3}, "413": {"movie_id": 236, "timestamp": 969810337, "Genre": "Comedy|Romance", "movie_name": "French Kiss (1995)", "rating": 2}, "414": {"movie_id": 1285, "timestamp": 969811993, "Genre": "Comedy", "movie_name": "Heathers (1989)", "rating": 5}, "415": {"movie_id": 252, "timestamp": 969810168, "Genre": "Comedy|Romance", "movie_name": "I.Q. (1994)", "rating": 2}, "416": {"movie_id": 3614, "timestamp": 1015018938, "Genre": "Comedy|Romance", "movie_name": "Honeymoon in Vegas (1992)", "rating": 2}, "417": {"movie_id": 3543, "timestamp": 969812188, "Genre": "Comedy|Drama", "movie_name": "Diner (1982)", "rating": 5}, "418": {"movie_id": 3040, "timestamp": 1015018190, "Genre": "Comedy", "movie_name": "Meatballs (1979)", "rating": 3}, "419": {"movie_id": 2247, "timestamp": 1015018854, "Genre": "Comedy", "movie_name": "Married to the Mob (1988)", "rating": 1}, "420": {"movie_id": 413, "timestamp": 969810376, "Genre": "Comedy", "movie_name": "Airheads (1994)", "rating": 4}, "421": {"movie_id": 1457, "timestamp": 1015019559, "Genre": "Comedy|Romance", "movie_name": "Fools Rush In (1997)", "rating": 1}, "422": {"movie_id": 852, "timestamp": 969810070, "Genre": "Comedy|Romance", "movie_name": "Tin Cup (1996)", "rating": 1}, "423": {"movie_id": 2262, "timestamp": 1015019283, "Genre": "Comedy|Drama|Romance", "movie_name": "About Last Night... (1986)", "rating": 3}, "424": {"movie_id": 518, "timestamp": 969810401, "Genre": "Comedy", "movie_name": "Road to Wellville, The (1994)", "rating": 2}, "425": {"movie_id": 3152, "timestamp": 976306953, "Genre": "Drama", "movie_name": "Last Picture Show, The (1971)", "rating": 5}, "426": {"movie_id": 471, "timestamp": 969809964, "Genre": "Comedy|Romance", "movie_name": "Hudsucker Proxy, The (1994)", "rating": 5}, "427": {"movie_id": 3690, "timestamp": 969808880, "Genre": "Comedy", "movie_name": "Porky's Revenge (1985)", "rating": 1}, "428": {"movie_id": 550, "timestamp": 1015018915, "Genre": "Comedy|Romance", "movie_name": "Threesome (1994)", "rating": 1}, "429": {"movie_id": 3263, "timestamp": 969810107, "Genre": "Comedy", "movie_name": "White Men Can't Jump (1992)", "rating": 4}, "430": {"movie_id": 2463, "timestamp": 969812469, "Genre": "Comedy", "movie_name": "Ruthless People (1986)", "rating": 4}, "431": {"movie_id": 2473, "timestamp": 969808940, "Genre": "Comedy", "movie_name": "Soul Man (1986)", "rating": 2}, "432": {"movie_id": 3364, "timestamp": 976302495, "Genre": "Crime|Film-Noir", "movie_name": "Asphalt Jungle, The (1950)", "rating": 4}, "433": {"movie_id": 922, "timestamp": 976302319, "Genre": "Film-Noir", "movie_name": "Sunset Blvd. (a.k.a. Sunset Boulevard) (1950)", "rating": 5}, "434": {"movie_id": 2186, "timestamp": 976302319, "Genre": "Film-Noir|Thriller", "movie_name": "Strangers on a Train (1951)", "rating": 5}, "435": {"movie_id": 3683, "timestamp": 976302319, "Genre": "Drama|Film-Noir", "movie_name": "Blood Simple (1984)", "rating": 4}, "436": {"movie_id": 144, "timestamp": 1015018465, "Genre": "Comedy", "movie_name": "Brothers McMullen, The (1995)", "rating": 3}, "437": {"movie_id": 928, "timestamp": 976306513, "Genre": "Romance|Thriller", "movie_name": "Rebecca (1940)", "rating": 5}, "438": {"movie_id": 1208, "timestamp": 976307639, "Genre": "Drama|War", "movie_name": "Apocalypse Now (1979)", "rating": 5}, "439": {"movie_id": 2944, "timestamp": 976308152, "Genre": "Action|War", "movie_name": "Dirty Dozen, The (1967)", "rating": 5}, "440": {"movie_id": 1176, "timestamp": 969810818, "Genre": "Drama", "movie_name": "Double Life of Veronique, The (La Double Vie de V\u00e9ronique) (1991)", "rating": 3}, "441": {"movie_id": 3949, "timestamp": 1008794639, "Genre": "Drama", "movie_name": "Requiem for a Dream (2000)", "rating": 5}, "442": {"movie_id": 1041, "timestamp": 969811195, "Genre": "Drama", "movie_name": "Secrets & Lies (1996)", "rating": 3}, "443": {"movie_id": 3028, "timestamp": 969812311, "Genre": "Comedy", "movie_name": "Taming of the Shrew, The (1967)", "rating": 5}, "444": {"movie_id": 1281, "timestamp": 976306436, "Genre": "Comedy", "movie_name": "Great Dictator, The (1940)", "rating": 5}, "445": {"movie_id": 3462, "timestamp": 969812092, "Genre": "Comedy", "movie_name": "Modern Times (1936)", "rating": 5}, "446": {"movie_id": 3200, "timestamp": 969812350, "Genre": "Comedy|Drama", "movie_name": "Last Detail, The (1973)", "rating": 4}, "447": {"movie_id": 933, "timestamp": 969812188, "Genre": "Comedy|Romance|Thriller", "movie_name": "To Catch a Thief (1955)", "rating": 5}, "448": {"movie_id": 2922, "timestamp": 976307476, "Genre": "Western", "movie_name": "Hang 'em High (1967)", "rating": 5}, "449": {"movie_id": 1235, "timestamp": 969811779, "Genre": "Comedy", "movie_name": "Harold and Maude (1971)", "rating": 5}, "450": {"movie_id": 3429, "timestamp": 969811779, "Genre": "Animation|Comedy", "movie_name": "Creature Comforts (1990)", "rating": 5}, "451": {"movie_id": 3504, "timestamp": 969811842, "Genre": "Comedy|Drama", "movie_name": "Network (1976)", "rating": 5}, "452": {"movie_id": 154, "timestamp": 1011373511, "Genre": "Drama", "movie_name": "Belle de jour (1967)", "rating": 4}, "453": {"movie_id": 1333, "timestamp": 976307639, "Genre": "Horror", "movie_name": "Birds, The (1963)", "rating": 4}, "454": {"movie_id": 3019, "timestamp": 976307655, "Genre": "Crime|Drama", "movie_name": "Drugstore Cowboy (1989)", "rating": 5}, "455": {"movie_id": 2303, "timestamp": 1011371751, "Genre": "Drama|Musical", "movie_name": "Nashville (1975)", "rating": 3}, "456": {"movie_id": 1299, "timestamp": 976307257, "Genre": "Drama|War", "movie_name": "Killing Fields, The (1984)", "rating": 5}, "457": {"movie_id": 2926, "timestamp": 969812350, "Genre": "Comedy|Drama", "movie_name": "Hairspray (1988)", "rating": 5}, "458": {"movie_id": 3760, "timestamp": 969812606, "Genre": "Comedy", "movie_name": "Kentucky Fried Movie, The (1977)", "rating": 4}, "459": {"movie_id": 3693, "timestamp": 1015019269, "Genre": "Comedy|Horror", "movie_name": "Toxic Avenger, The (1985)", "rating": 4}, "460": {"movie_id": 1300, "timestamp": 976307180, "Genre": "Drama", "movie_name": "My Life as a Dog (Mitt liv som hund) (1985)", "rating": 5}, "461": {"movie_id": 1231, "timestamp": 976307303, "Genre": "Drama", "movie_name": "Right Stuff, The (1983)", "rating": 5}, "462": {"movie_id": 3271, "timestamp": 969811155, "Genre": "Drama", "movie_name": "Of Mice and Men (1992)", "rating": 3}, "463": {"movie_id": 2796, "timestamp": 1015019457, "Genre": "Comedy", "movie_name": "Funny Farm (1988)", "rating": 1}, "464": {"movie_id": 3365, "timestamp": 976306953, "Genre": "Western", "movie_name": "Searchers, The (1956)", "rating": 4}, "465": {"movie_id": 2575, "timestamp": 969811100, "Genre": "Drama", "movie_name": "Dreamlife of Angels, The (La Vie r\u00eav\u00e9e des anges) (1998)", "rating": 5}, "466": {"movie_id": 1964, "timestamp": 976307589, "Genre": "Drama|Mystery", "movie_name": "Klute (1971)", "rating": 4}, "467": {"movie_id": 3060, "timestamp": 969809781, "Genre": "Comedy|Drama", "movie_name": "Commitments, The (1991)", "rating": 3}, "468": {"movie_id": 2919, "timestamp": 976308131, "Genre": "Drama|Romance", "movie_name": "Year of Living Dangerously (1982)", "rating": 4}, "469": {"movie_id": 3649, "timestamp": 976302972, "Genre": "Drama", "movie_name": "American Gigolo (1980)", "rating": 4}, "470": {"movie_id": 965, "timestamp": 976306953, "Genre": "Thriller", "movie_name": "39 Steps, The (1935)", "rating": 5}, "471": {"movie_id": 2611, "timestamp": 969811264, "Genre": "Drama", "movie_name": "Winslow Boy, The (1998)", "rating": 3}, "472": {"movie_id": 1172, "timestamp": 969811961, "Genre": "Comedy|Drama|Romance", "movie_name": "Cinema Paradiso (1988)", "rating": 5}, "473": {"movie_id": 2155, "timestamp": 1015017666, "Genre": "Comedy", "movie_name": "Slums of Beverly Hills, The (1998)", "rating": 5}, "474": {"movie_id": 3706, "timestamp": 976302566, "Genre": "Film-Noir|Mystery|Thriller", "movie_name": "Angel Heart (1987)", "rating": 4}, "475": {"movie_id": 1963, "timestamp": 976301511, "Genre": "Comedy", "movie_name": "Take the Money and Run (1969)", "rating": 5}, "476": {"movie_id": 2774, "timestamp": 969809806, "Genre": "Comedy|Romance", "movie_name": "Better Than Chocolate (1999)", "rating": 3}, "477": {"movie_id": 1147, "timestamp": 969810912, "Genre": "Documentary", "movie_name": "When We Were Kings (1996)", "rating": 5}, "478": {"movie_id": 3196, "timestamp": 1011372971, "Genre": "Drama|War", "movie_name": "Stalag 17 (1953)", "rating": 4}, "479": {"movie_id": 2677, "timestamp": 969810818, "Genre": "Documentary", "movie_name": "Buena Vista Social Club (1999)", "rating": 4}, "480": {"movie_id": 1952, "timestamp": 976306513, "Genre": "Drama", "movie_name": "Midnight Cowboy (1969)", "rating": 5}, "481": {"movie_id": 107, "timestamp": 969810070, "Genre": "Adventure|Children's|Comedy|Musical", "movie_name": "Muppet Treasure Island (1996)", "rating": 3}, "482": {"movie_id": 305, "timestamp": 1015019467, "Genre": "Comedy", "movie_name": "Ready to Wear (Pret-A-Porter) (1994)", "rating": 2}, "483": {"movie_id": 909, "timestamp": 976301973, "Genre": "Comedy|Drama", "movie_name": "Apartment, The (1960)", "rating": 5}, "484": {"movie_id": 3045, "timestamp": 969810422, "Genre": "Comedy|Drama", "movie_name": "Peter's Friends (1992)", "rating": 1}, "485": {"movie_id": 835, "timestamp": 969811646, "Genre": "Drama", "movie_name": "Foxfire (1996)", "rating": 4}, "486": {"movie_id": 3477, "timestamp": 969810070, "Genre": "Comedy|Drama", "movie_name": "Empire Records (1995)", "rating": 4}, "487": {"movie_id": 514, "timestamp": 969809866, "Genre": "Comedy", "movie_name": "Ref, The (1994)", "rating": 5}, "488": {"movie_id": 3617, "timestamp": 1015018645, "Genre": "Comedy", "movie_name": "Road Trip (2000)", "rating": 1}, "489": {"movie_id": 1190, "timestamp": 969811671, "Genre": "Drama", "movie_name": "Tie Me Up! Tie Me Down! (1990)", "rating": 3}, "490": {"movie_id": 1648, "timestamp": 969810002, "Genre": "Comedy|Drama|Thriller", "movie_name": "House of Yes, The (1997)", "rating": 4}, "491": {"movie_id": 1816, "timestamp": 1015019325, "Genre": "Comedy|Drama", "movie_name": "Two Girls and a Guy (1997)", "rating": 2}, "492": {"movie_id": 307, "timestamp": 976307898, "Genre": "Drama", "movie_name": "Three Colors: Blue (1993)", "rating": 4}, "493": {"movie_id": 322, "timestamp": 969811301, "Genre": "Comedy|Drama", "movie_name": "Swimming with Sharks (1995)", "rating": 5}, "494": {"movie_id": 190, "timestamp": 976307325, "Genre": "Thriller", "movie_name": "Safe (1995)", "rating": 4}, "495": {"movie_id": 2750, "timestamp": 969812311, "Genre": "Comedy|Drama", "movie_name": "Radio Days (1987)", "rating": 4}, "496": {"movie_id": 281, "timestamp": 969811443, "Genre": "Drama", "movie_name": "Nobody's Fool (1994)", "rating": 4}, "497": {"movie_id": 290, "timestamp": 1016049347, "Genre": "Crime|Drama", "movie_name": "Once Were Warriors (1994)", "rating": 4}, "498": {"movie_id": 456, "timestamp": 969811060, "Genre": "Drama", "movie_name": "Fresh (1994)", "rating": 5}, "499": {"movie_id": 1211, "timestamp": 969812311, "Genre": "Comedy|Drama|Romance", "movie_name": "Wings of Desire (Der Himmel \u00fcber Berlin) (1987)", "rating": 5}, "500": {"movie_id": 482, "timestamp": 976307429, "Genre": "Thriller", "movie_name": "Killing Zoe (1994)", "rating": 3}, "501": {"movie_id": 2788, "timestamp": 976301973, "Genre": "Comedy", "movie_name": "And Now for Something Completely Different (1971)", "rating": 5}, "502": {"movie_id": 1228, "timestamp": 976307209, "Genre": "Drama", "movie_name": "Raging Bull (1980)", "rating": 5}, "503": {"movie_id": 3328, "timestamp": 1037310511, "Genre": "Crime|Drama", "movie_name": "Ghost Dog: The Way of the Samurai (1999)", "rating": 5}, "504": {"movie_id": 3089, "timestamp": 976303707, "Genre": "Drama", "movie_name": "Bicycle Thief, The (Ladri di biciclette) (1948)", "rating": 5}, "505": {"movie_id": 3742, "timestamp": 976306302, "Genre": "Drama|War", "movie_name": "Battleship Potemkin, The (Bronenosets Potyomkin) (1925)", "rating": 5}, "506": {"movie_id": 3882, "timestamp": 1008794952, "Genre": "Comedy", "movie_name": "Bring It On (2000)", "rating": 3}, "507": {"movie_id": 3317, "timestamp": 1044313689, "Genre": "Comedy|Drama", "movie_name": "Wonder Boys (2000)", "rating": 4}, "508": {"movie_id": 2819, "timestamp": 1011373848, "Genre": "Thriller", "movie_name": "Three Days of the Condor (1975)", "rating": 4}, "509": {"movie_id": 3007, "timestamp": 1008795546, "Genre": "Documentary", "movie_name": "American Movie (1999)", "rating": 5}, "510": {"movie_id": 166, "timestamp": 1015019241, "Genre": "Comedy|Drama", "movie_name": "Doom Generation, The (1995)", "rating": 3}, "511": {"movie_id": 3783, "timestamp": 1008794639, "Genre": "Crime|Drama", "movie_name": "Croupier (1998)", "rating": 3}}, "train": {"0": {"movie_id": 1193, "timestamp": 976306894, "Genre": "Drama", "movie_name": "One Flew Over the Cuckoo's Nest (1975)", "rating": 5}, "1": {"movie_id": 3408, "timestamp": 1008794776, "Genre": "Drama", "movie_name": "Erin Brockovich (2000)", "rating": 4}, "2": {"movie_id": 1197, "timestamp": 969811879, "Genre": "Action|Adventure|Comedy|Romance", "movie_name": "Princess Bride, The (1987)", "rating": 5}, "3": {"movie_id": 919, "timestamp": 976307127, "Genre": "Adventure|Children's|Drama|Musical", "movie_name": "Wizard of Oz, The (1939)", "rating": 5}, "4": {"movie_id": 2918, "timestamp": 969812120, "Genre": "Comedy", "movie_name": "Ferris Bueller's Day Off (1986)", "rating": 5}, "5": {"movie_id": 2791, "timestamp": 969811842, "Genre": "Comedy", "movie_name": "Airplane! (1980)", "rating": 5}, "6": {"movie_id": 2797, "timestamp": 969812381, "Genre": "Comedy|Fantasy", "movie_name": "Big (1988)", "rating": 5}, "7": {"movie_id": 2321, "timestamp": 969811132, "Genre": "Comedy", "movie_name": "Pleasantville (1998)", "rating": 4}, "8": {"movie_id": 720, "timestamp": 969810679, "Genre": "Animation", "movie_name": "Wallace & Gromit: The Best of Aardman Animation (1996)", "rating": 5}, "9": {"movie_id": 1270, "timestamp": 969811961, "Genre": "Comedy|Sci-Fi", "movie_name": "Back to the Future (1985)", "rating": 3}, "10": {"movie_id": 1097, "timestamp": 976302689, "Genre": "Children's|Drama|Fantasy|Sci-Fi", "movie_name": "E.T. the Extra-Terrestrial (1982)", "rating": 5}, "11": {"movie_id": 1545, "timestamp": 1011373829, "Genre": "Drama", "movie_name": "Ponette (1996)", "rating": 3}, "12": {"movie_id": 745, "timestamp": 969809357, "Genre": "Animation|Comedy|Thriller", "movie_name": "Close Shave, A (1995)", "rating": 5}, "13": {"movie_id": 2762, "timestamp": 969810836, "Genre": "Thriller", "movie_name": "Sixth Sense, The (1999)", "rating": 4}, "14": {"movie_id": 1961, "timestamp": 969808940, "Genre": "Drama", "movie_name": "Rain Man (1988)", "rating": 3}, "15": {"movie_id": 2692, "timestamp": 969811042, "Genre": "Action|Crime|Romance", "movie_name": "Run Lola Run (Lola rennt) (1998)", "rating": 5}, "16": {"movie_id": 260, "timestamp": 972685452, "Genre": "Action|Adventure|Fantasy|Sci-Fi", "movie_name": "Star Wars: Episode IV - A New Hope (1977)", "rating": 5}, "17": {"movie_id": 1028, "timestamp": 969812441, "Genre": "Children's|Comedy|Musical", "movie_name": "Mary Poppins (1964)", "rating": 5}, "18": {"movie_id": 1207, "timestamp": 976303836, "Genre": "Drama", "movie_name": "To Kill a Mockingbird (1962)", "rating": 5}, "19": {"movie_id": 2028, "timestamp": 969808880, "Genre": "Action|Drama|War", "movie_name": "Saving Private Ryan (1998)", "rating": 4}, "20": {"movie_id": 608, "timestamp": 969810679, "Genre": "Crime|Drama|Thriller", "movie_name": "Fargo (1996)", "rating": 5}, "21": {"movie_id": 3068, "timestamp": 976307058, "Genre": "Drama", "movie_name": "Verdict, The (1982)", "rating": 5}, "22": {"movie_id": 1103, "timestamp": 976307898, "Genre": "Drama", "movie_name": "Rebel Without a Cause (1955)", "rating": 5}, "23": {"movie_id": 2916, "timestamp": 969811321, "Genre": "Action|Adventure|Sci-Fi|Thriller", "movie_name": "Total Recall (1990)", "rating": 4}, "24": {"movie_id": 3468, "timestamp": 976307589, "Genre": "Drama", "movie_name": "Hustler, The (1961)", "rating": 5}, "25": {"movie_id": 1213, "timestamp": 976306436, "Genre": "Crime|Drama", "movie_name": "GoodFellas (1990)", "rating": 5}, "26": {"movie_id": 3578, "timestamp": 1008794820, "Genre": "Action|Drama", "movie_name": "Gladiator (2000)", "rating": 4}, "27": {"movie_id": 3108, "timestamp": 969809781, "Genre": "Comedy|Drama|Romance", "movie_name": "Fisher King, The (1991)", "rating": 3}, "28": {"movie_id": 3035, "timestamp": 969812064, "Genre": "Comedy|Drama|War", "movie_name": "Mister Roberts (1955)", "rating": 5}, "29": {"movie_id": 1610, "timestamp": 969810885, "Genre": "Action|Thriller", "movie_name": "Hunt for Red October, The (1990)", "rating": 2}, "30": {"movie_id": 368, "timestamp": 969810150, "Genre": "Action|Comedy|Western", "movie_name": "Maverick (1994)", "rating": 3}, "31": {"movie_id": 1259, "timestamp": 969812032, "Genre": "Adventure|Comedy|Drama", "movie_name": "Stand by Me (1986)", "rating": 5}, "32": {"movie_id": 1188, "timestamp": 969809715, "Genre": "Comedy|Romance", "movie_name": "Strictly Ballroom (1992)", "rating": 4}, "33": {"movie_id": 3255, "timestamp": 969809936, "Genre": "Comedy|Drama", "movie_name": "League of Their Own, A (1992)", "rating": 3}, "34": {"movie_id": 110, "timestamp": 969810912, "Genre": "Action|Drama|War", "movie_name": "Braveheart (1995)", "rating": 4}, "35": {"movie_id": 1834, "timestamp": 969811132, "Genre": "Drama|Thriller", "movie_name": "Spanish Prisoner, The (1997)", "rating": 3}, "36": {"movie_id": 3471, "timestamp": 1011373890, "Genre": "Drama|Sci-Fi", "movie_name": "Close Encounters of the Third Kind (1977)", "rating": 4}, "37": {"movie_id": 589, "timestamp": 1011373809, "Genre": "Action|Sci-Fi|Thriller", "movie_name": "Terminator 2: Judgment Day (1991)", "rating": 4}, "38": {"movie_id": 1945, "timestamp": 976307944, "Genre": "Crime|Drama", "movie_name": "On the Waterfront (1954)", "rating": 5}, "39": {"movie_id": 2858, "timestamp": 969809371, "Genre": "Comedy|Drama", "movie_name": "American Beauty (1999)", "rating": 5}, "40": {"movie_id": 515, "timestamp": 1011373890, "Genre": "Drama", "movie_name": "Remains of the Day, The (1993)", "rating": 3}, "41": {"movie_id": 265, "timestamp": 969810885, "Genre": "Drama|Romance", "movie_name": "Like Water for Chocolate (Como agua para chocolate) (1992)", "rating": 5}, "42": {"movie_id": 1084, "timestamp": 976307085, "Genre": "Crime|Drama", "movie_name": "Bonnie and Clyde (1967)", "rating": 5}, "43": {"movie_id": 480, "timestamp": 969811426, "Genre": "Action|Adventure|Sci-Fi", "movie_name": "Jurassic Park (1993)", "rating": 3}, "44": {"movie_id": 2067, "timestamp": 1011373908, "Genre": "Drama|Romance|War", "movie_name": "Doctor Zhivago (1965)", "rating": 4}, "45": {"movie_id": 1265, "timestamp": 969809532, "Genre": "Comedy|Romance", "movie_name": "Groundhog Day (1993)", "rating": 5}, "46": {"movie_id": 3334, "timestamp": 976302495, "Genre": "Crime|Drama|Film-Noir|Thriller", "movie_name": "Key Largo (1948)", "rating": 4}, "47": {"movie_id": 1196, "timestamp": 976307325, "Genre": "Action|Adventure|Drama|Sci-Fi|War", "movie_name": "Star Wars: Episode V - The Empire Strikes Back (1980)", "rating": 5}, "48": {"movie_id": 1198, "timestamp": 976307589, "Genre": "Action|Adventure", "movie_name": "Raiders of the Lost Ark (1981)", "rating": 5}, "49": {"movie_id": 593, "timestamp": 969810736, "Genre": "Drama|Thriller", "movie_name": "Silence of the Lambs, The (1991)", "rating": 5}, "50": {"movie_id": 2571, "timestamp": 969810967, "Genre": "Action|Sci-Fi|Thriller", "movie_name": "Matrix, The (1999)", "rating": 5}, "51": {"movie_id": 2396, "timestamp": 969809458, "Genre": "Comedy|Romance", "movie_name": "Shakespeare in Love (1998)", "rating": 5}, "52": {"movie_id": 3735, "timestamp": 976307180, "Genre": "Crime|Drama", "movie_name": "Serpico (1973)", "rating": 4}, "53": {"movie_id": 1953, "timestamp": 976307476, "Genre": "Action|Crime|Drama|Thriller", "movie_name": "French Connection, The (1971)", "rating": 5}, "54": {"movie_id": 3809, "timestamp": 969809964, "Genre": "Comedy", "movie_name": "What About Bob? (1991)", "rating": 5}, "55": {"movie_id": 235, "timestamp": 969809532, "Genre": "Comedy|Drama", "movie_name": "Ed Wood (1994)", "rating": 4}, "56": {"movie_id": 163, "timestamp": 969811626, "Genre": "Action|Romance|Thriller", "movie_name": "Desperado (1995)", "rating": 4}, "57": {"movie_id": 21, "timestamp": 969809748, "Genre": "Action|Comedy|Drama", "movie_name": "Get Shorty (1995)", "rating": 3}, "58": {"movie_id": 380, "timestamp": 969810150, "Genre": "Action|Adventure|Comedy|Romance", "movie_name": "True Lies (1994)", "rating": 3}, "59": {"movie_id": 2501, "timestamp": 1018892920, "Genre": "Drama", "movie_name": "October Sky (1999)", "rating": 1}, "60": {"movie_id": 457, "timestamp": 969811100, "Genre": "Action|Thriller", "movie_name": "Fugitive, The (1993)", "rating": 3}, "61": {"movie_id": 1096, "timestamp": 976307944, "Genre": "Drama", "movie_name": "Sophie's Choice (1982)", "rating": 5}, "62": {"movie_id": 1527, "timestamp": 969811671, "Genre": "Action|Sci-Fi", "movie_name": "Fifth Element, The (1997)", "rating": 3}, "63": {"movie_id": 3418, "timestamp": 969811264, "Genre": "Action|Drama", "movie_name": "Thelma & Louise (1991)", "rating": 4}, "64": {"movie_id": 2002, "timestamp": 969810301, "Genre": "Action|Comedy|Crime|Drama", "movie_name": "Lethal Weapon 3 (1992)", "rating": 3}, "65": {"movie_id": 1784, "timestamp": 969809844, "Genre": "Comedy|Drama", "movie_name": "As Good As It Gets (1997)", "rating": 4}, "66": {"movie_id": 318, "timestamp": 969810656, "Genre": "Drama", "movie_name": "Shawshank Redemption, The (1994)", "rating": 5}, "67": {"movie_id": 1968, "timestamp": 1015017684, "Genre": "Comedy|Drama", "movie_name": "Breakfast Club, The (1985)", "rating": 4}, "68": {"movie_id": 1244, "timestamp": 969811915, "Genre": "Comedy|Drama|Romance", "movie_name": "Manhattan (1979)", "rating": 4}, "69": {"movie_id": 356, "timestamp": 1015018190, "Genre": "Comedy|Romance|War", "movie_name": "Forrest Gump (1994)", "rating": 2}, "70": {"movie_id": 1245, "timestamp": 969810818, "Genre": "Drama", "movie_name": "Miller's Crossing (1990)", "rating": 3}, "71": {"movie_id": 1247, "timestamp": 976306653, "Genre": "Drama|Romance", "movie_name": "Graduate, The (1967)", "rating": 5}, "72": {"movie_id": 3421, "timestamp": 969811842, "Genre": "Comedy", "movie_name": "Animal House (1978)", "rating": 5}, "73": {"movie_id": 1641, "timestamp": 969811347, "Genre": "Comedy", "movie_name": "Full Monty, The (1997)", "rating": 3}, "74": {"movie_id": 1394, "timestamp": 969811842, "Genre": "Comedy", "movie_name": "Raising Arizona (1987)", "rating": 5}, "75": {"movie_id": 104, "timestamp": 969810025, "Genre": "Comedy", "movie_name": "Happy Gilmore (1996)", "rating": 5}, "76": {"movie_id": 3868, "timestamp": 969812232, "Genre": "Comedy", "movie_name": "Naked Gun: From the Files of Police Squad!, The (1988)", "rating": 5}, "77": {"movie_id": 1079, "timestamp": 969811879, "Genre": "Comedy", "movie_name": "Fish Called Wanda, A (1988)", "rating": 5}, "78": {"movie_id": 2997, "timestamp": 969811779, "Genre": "Comedy", "movie_name": "Being John Malkovich (1999)", "rating": 5}, "79": {"movie_id": 1580, "timestamp": 969809964, "Genre": "Action|Adventure|Comedy|Sci-Fi", "movie_name": "Men in Black (1997)", "rating": 3}, "80": {"movie_id": 1266, "timestamp": 969810885, "Genre": "Western", "movie_name": "Unforgiven (1992)", "rating": 4}, "81": {"movie_id": 1378, "timestamp": 1015019004, "Genre": "Action|Comedy|Western", "movie_name": "Young Guns (1988)", "rating": 3}, "82": {"movie_id": 3552, "timestamp": 969812288, "Genre": "Comedy", "movie_name": "Caddyshack (1980)", "rating": 5}, "83": {"movie_id": 1304, "timestamp": 969811842, "Genre": "Action|Comedy|Western", "movie_name": "Butch Cassidy and the Sundance Kid (1969)", "rating": 5}, "84": {"movie_id": 3671, "timestamp": 969811961, "Genre": "Comedy|Western", "movie_name": "Blazing Saddles (1974)", "rating": 5}, "85": {"movie_id": 2871, "timestamp": 976307429, "Genre": "Adventure|Thriller", "movie_name": "Deliverance (1972)", "rating": 5}, "86": {"movie_id": 1136, "timestamp": 969811813, "Genre": "Comedy", "movie_name": "Monty Python and the Holy Grail (1974)", "rating": 5}, "87": {"movie_id": 2951, "timestamp": 976307746, "Genre": "Action|Western", "movie_name": "Fistful of Dollars, A (1964)", "rating": 4}, "88": {"movie_id": 1214, "timestamp": 976307639, "Genre": "Action|Horror|Sci-Fi|Thriller", "movie_name": "Alien (1979)", "rating": 5}, "89": {"movie_id": 1387, "timestamp": 1011373867, "Genre": "Action|Horror", "movie_name": "Jaws (1975)", "rating": 4}, "90": {"movie_id": 1201, "timestamp": 976307209, "Genre": "Action|Western", "movie_name": "Good, The Bad and The Ugly, The (1966)", "rating": 5}, "91": {"movie_id": 1240, "timestamp": 1011373657, "Genre": "Action|Sci-Fi|Thriller", "movie_name": "Terminator, The (1984)", "rating": 5}, "92": {"movie_id": 2987, "timestamp": 976302495, "Genre": "Adventure|Animation|Film-Noir", "movie_name": "Who Framed Roger Rabbit? (1988)", "rating": 4}, "93": {"movie_id": 1175, "timestamp": 969809532, "Genre": "Comedy|Sci-Fi", "movie_name": "Delicatessen (1991)", "rating": 5}, "94": {"movie_id": 39, "timestamp": 969809780, "Genre": "Comedy|Romance", "movie_name": "Clueless (1995)", "rating": 5}, "95": {"movie_id": 1466, "timestamp": 969811100, "Genre": "Crime|Drama", "movie_name": "Donnie Brasco (1997)", "rating": 3}, "96": {"movie_id": 866, "timestamp": 969810990, "Genre": "Crime|Drama|Romance|Thriller", "movie_name": "Bound (1996)", "rating": 4}, "97": {"movie_id": 501, "timestamp": 969811301, "Genre": "Drama", "movie_name": "Naked (1993)", "rating": 4}, "98": {"movie_id": 1250, "timestamp": 976307058, "Genre": "Drama|War", "movie_name": "Bridge on the River Kwai, The (1957)", "rating": 5}, "99": {"movie_id": 3793, "timestamp": 1008794793, "Genre": "Action|Sci-Fi", "movie_name": "X-Men (2000)", "rating": 3}, "100": {"movie_id": 509, "timestamp": 969811533, "Genre": "Drama|Romance", "movie_name": "Piano, The (1993)", "rating": 3}, "101": {"movie_id": 2058, "timestamp": 969811301, "Genre": "Action|Thriller", "movie_name": "Negotiator, The (1998)", "rating": 5}, "102": {"movie_id": 47, "timestamp": 969810818, "Genre": "Crime|Thriller", "movie_name": "Seven (Se7en) (1995)", "rating": 3}, "103": {"movie_id": 2700, "timestamp": 969809715, "Genre": "Animation|Comedy", "movie_name": "South Park: Bigger, Longer and Uncut (1999)", "rating": 5}, "104": {"movie_id": 296, "timestamp": 969810736, "Genre": "Crime|Drama", "movie_name": "Pulp Fiction (1994)", "rating": 5}, "105": {"movie_id": 1617, "timestamp": 969810656, "Genre": "Crime|Film-Noir|Mystery|Thriller", "movie_name": "L.A. Confidential (1997)", "rating": 4}, "106": {"movie_id": 728, "timestamp": 969810128, "Genre": "Comedy", "movie_name": "Cold Comfort Farm (1995)", "rating": 3}, "107": {"movie_id": 224, "timestamp": 969811600, "Genre": "Comedy|Drama|Romance", "movie_name": "Don Juan DeMarco (1995)", "rating": 3}, "108": {"movie_id": 6, "timestamp": 969808940, "Genre": "Action|Crime|Thriller", "movie_name": "Heat (1995)", "rating": 2}, "109": {"movie_id": 3006, "timestamp": 1008795614, "Genre": "Drama", "movie_name": "Insider, The (1999)", "rating": 4}, "110": {"movie_id": 800, "timestamp": 969810860, "Genre": "Drama|Mystery", "movie_name": "Lone Star (1996)", "rating": 5}, "111": {"movie_id": 50, "timestamp": 969810656, "Genre": "Crime|Thriller", "movie_name": "Usual Suspects, The (1995)", "rating": 5}, "112": {"movie_id": 1192, "timestamp": 1011373848, "Genre": "Documentary", "movie_name": "Paris Is Burning (1990)", "rating": 3}, "113": {"movie_id": 1268, "timestamp": 969811533, "Genre": "Drama", "movie_name": "Pump Up the Volume (1990)", "rating": 3}, "114": {"movie_id": 3083, "timestamp": 1015016589, "Genre": "Comedy|Drama", "movie_name": "All About My Mother (Todo Sobre Mi Madre) (1999)", "rating": 2}, "115": {"movie_id": 2282, "timestamp": 969809844, "Genre": "Comedy|Drama", "movie_name": "Pecker (1998)", "rating": 4}, "116": {"movie_id": 1912, "timestamp": 969810783, "Genre": "Action|Crime|Romance", "movie_name": "Out of Sight (1998)", "rating": 4}, "117": {"movie_id": 2716, "timestamp": 969812158, "Genre": "Comedy|Horror", "movie_name": "Ghostbusters (1984)", "rating": 5}, "118": {"movie_id": 2289, "timestamp": 969809458, "Genre": "Comedy|Drama", "movie_name": "Player, The (1992)", "rating": 5}, "119": {"movie_id": 162, "timestamp": 969810912, "Genre": "Documentary", "movie_name": "Crumb (1994)", "rating": 5}, "120": {"movie_id": 1704, "timestamp": 969811060, "Genre": "Drama", "movie_name": "Good Will Hunting (1997)", "rating": 5}, "121": {"movie_id": 2291, "timestamp": 969811060, "Genre": "Drama|Romance", "movie_name": "Edward Scissorhands (1990)", "rating": 5}, "122": {"movie_id": 1635, "timestamp": 969810860, "Genre": "Drama", "movie_name": "Ice Storm, The (1997)", "rating": 5}, "123": {"movie_id": 2723, "timestamp": 969810107, "Genre": "Action|Adventure|Comedy", "movie_name": "Mystery Men (1999)", "rating": 3}, "124": {"movie_id": 1923, "timestamp": 969809577, "Genre": "Comedy", "movie_name": "There's Something About Mary (1998)", "rating": 5}, "125": {"movie_id": 2580, "timestamp": 969810860, "Genre": "Crime", "movie_name": "Go (1999)", "rating": 4}, "126": {"movie_id": 3386, "timestamp": 1018893016, "Genre": "Drama|Mystery", "movie_name": "JFK (1991)", "rating": 4}, "127": {"movie_id": 176, "timestamp": 969810967, "Genre": "Comedy", "movie_name": "Living in Oblivion (1995)", "rating": 5}, "128": {"movie_id": 1429, "timestamp": 969811264, "Genre": "Action", "movie_name": "Jackie Chan's First Strike (1996)", "rating": 3}, "129": {"movie_id": 1719, "timestamp": 969810783, "Genre": "Drama", "movie_name": "Sweet Hereafter, The (1997)", "rating": 5}, "130": {"movie_id": 1649, "timestamp": 969810942, "Genre": "Documentary", "movie_name": "Fast, Cheap & Out of Control (1997)", "rating": 3}, "131": {"movie_id": 2599, "timestamp": 969810748, "Genre": "Comedy", "movie_name": "Election (1999)", "rating": 4}, "132": {"movie_id": 1500, "timestamp": 969809629, "Genre": "Comedy|Crime", "movie_name": "Grosse Pointe Blank (1997)", "rating": 5}, "133": {"movie_id": 2959, "timestamp": 969810860, "Genre": "Drama", "movie_name": "Fight Club (1999)", "rating": 4}, "134": {"movie_id": 908, "timestamp": 976306953, "Genre": "Drama|Thriller", "movie_name": "North by Northwest (1959)", "rating": 5}, "135": {"movie_id": 16, "timestamp": 969811278, "Genre": "Drama|Thriller", "movie_name": "Casino (1995)", "rating": 3}, "136": {"movie_id": 194, "timestamp": 969811475, "Genre": "Drama", "movie_name": "Smoke (1995)", "rating": 3}, "137": {"movie_id": 551, "timestamp": 969809748, "Genre": "Children's|Comedy|Musical", "movie_name": "Nightmare Before Christmas, The (1993)", "rating": 4}, "138": {"movie_id": 1517, "timestamp": 969809715, "Genre": "Comedy", "movie_name": "Austin Powers: International Man of Mystery (1997)", "rating": 5}, "139": {"movie_id": 1089, "timestamp": 976307280, "Genre": "Crime|Thriller", "movie_name": "Reservoir Dogs (1992)", "rating": 4}, "140": {"movie_id": 3260, "timestamp": 969811401, "Genre": "Drama", "movie_name": "Howards End (1992)", "rating": 3}, "141": {"movie_id": 913, "timestamp": 976302319, "Genre": "Film-Noir|Mystery", "movie_name": "Maltese Falcon, The (1941)", "rating": 5}, "142": {"movie_id": 1449, "timestamp": 969809883, "Genre": "Comedy", "movie_name": "Waiting for Guffman (1996)", "rating": 5}, "143": {"movie_id": 1732, "timestamp": 969811498, "Genre": "Comedy|Crime|Mystery|Thriller", "movie_name": "Big Lebowski, The (1998)", "rating": 4}, "144": {"movie_id": 3267, "timestamp": 969811264, "Genre": "Action|Thriller", "movie_name": "Mariachi, El (1992)", "rating": 4}, "145": {"movie_id": 2395, "timestamp": 969809458, "Genre": "Comedy", "movie_name": "Rushmore (1998)", "rating": 5}, "146": {"movie_id": 1594, "timestamp": 969810885, "Genre": "Drama", "movie_name": "In the Company of Men (1997)", "rating": 2}, "147": {"movie_id": 2683, "timestamp": 969810261, "Genre": "Comedy", "movie_name": "Austin Powers: The Spy Who Shagged Me (1999)", "rating": 3}, "148": {"movie_id": 2759, "timestamp": 1015018728, "Genre": "Comedy", "movie_name": "Dick (1999)", "rating": 1}, "149": {"movie_id": 994, "timestamp": 969810912, "Genre": "Drama", "movie_name": "Big Night (1996)", "rating": 4}, "150": {"movie_id": 1885, "timestamp": 969809532, "Genre": "Comedy|Drama", "movie_name": "Opposite of Sex, The (1998)", "rating": 3}, "151": {"movie_id": 348, "timestamp": 969809629, "Genre": "Comedy", "movie_name": "Bullets Over Broadway (1994)", "rating": 2}, "152": {"movie_id": 29, "timestamp": 969810783, "Genre": "Adventure|Sci-Fi", "movie_name": "City of Lost Children, The (1995)", "rating": 5}, "153": {"movie_id": 562, "timestamp": 969809844, "Genre": "Comedy|Drama", "movie_name": "Welcome to the Dollhouse (1995)", "rating": 5}, "154": {"movie_id": 1095, "timestamp": 969810942, "Genre": "Drama", "movie_name": "Glengarry Glen Ross (1992)", "rating": 5}, "155": {"movie_id": 497, "timestamp": 969809748, "Genre": "Comedy|Romance", "movie_name": "Much Ado About Nothing (1993)", "rating": 3}, "156": {"movie_id": 1747, "timestamp": 969809844, "Genre": "Comedy|Drama", "movie_name": "Wag the Dog (1997)", "rating": 2}, "157": {"movie_id": 2908, "timestamp": 969810836, "Genre": "Drama", "movie_name": "Boys Don't Cry (1999)", "rating": 5}, "158": {"movie_id": 1966, "timestamp": 969809577, "Genre": "Comedy", "movie_name": "Metropolitan (1990)", "rating": 4}, "159": {"movie_id": 3499, "timestamp": 969811132, "Genre": "Horror", "movie_name": "Misery (1990)", "rating": 5}, "160": {"movie_id": 32, "timestamp": 969810818, "Genre": "Drama|Sci-Fi", "movie_name": "Twelve Monkeys (1995)", "rating": 3}, "161": {"movie_id": 1171, "timestamp": 969809964, "Genre": "Comedy", "movie_name": "Bob Roberts (1992)", "rating": 5}, "162": {"movie_id": 3786, "timestamp": 1008795233, "Genre": "Comedy", "movie_name": "But I'm a Cheerleader (1999)", "rating": 4}, "163": {"movie_id": 34, "timestamp": 969809458, "Genre": "Children's|Comedy|Drama", "movie_name": "Babe (1995)", "rating": 5}, "164": {"movie_id": 357, "timestamp": 969811671, "Genre": "Comedy|Romance", "movie_name": "Four Weddings and a Funeral (1994)", "rating": 1}, "165": {"movie_id": 36, "timestamp": 969811042, "Genre": "Drama", "movie_name": "Dead Man Walking (1995)", "rating": 3}, "166": {"movie_id": 714, "timestamp": 969810736, "Genre": "Western", "movie_name": "Dead Man (1995)", "rating": 3}, "167": {"movie_id": 3072, "timestamp": 1015017376, "Genre": "Comedy", "movie_name": "Moonstruck (1987)", "rating": 2}, "168": {"movie_id": 597, "timestamp": 969810376, "Genre": "Comedy|Romance", "movie_name": "Pretty Woman (1990)", "rating": 2}, "169": {"movie_id": 3524, "timestamp": 1015018986, "Genre": "Comedy|Romance", "movie_name": "Arthur (1981)", "rating": 2}, "170": {"movie_id": 3536, "timestamp": 1008794998, "Genre": "Comedy|Romance", "movie_name": "Keeping the Faith (2000)", "rating": 3}, "171": {"movie_id": 3685, "timestamp": 969812417, "Genre": "Comedy|Drama|Romance", "movie_name": "Prizzi's Honor (1985)", "rating": 4}, "172": {"movie_id": 1296, "timestamp": 976308091, "Genre": "Drama|Romance", "movie_name": "Room with a View, A (1986)", "rating": 4}, "173": {"movie_id": 2966, "timestamp": 976307344, "Genre": "Drama", "movie_name": "Straight Story, The (1999)", "rating": 4}, "174": {"movie_id": 17, "timestamp": 969811321, "Genre": "Drama|Romance", "movie_name": "Sense and Sensibility (1995)", "rating": 5}, "175": {"movie_id": 1441, "timestamp": 969810222, "Genre": "Comedy|Romance", "movie_name": "Benny & Joon (1993)", "rating": 3}, "176": {"movie_id": 912, "timestamp": 976303836, "Genre": "Drama|Romance|War", "movie_name": "Casablanca (1942)", "rating": 5}, "177": {"movie_id": 2469, "timestamp": 1015019169, "Genre": "Comedy|Romance", "movie_name": "Peggy Sue Got Married (1986)", "rating": 2}, "178": {"movie_id": 2100, "timestamp": 969812502, "Genre": "Comedy|Fantasy|Romance", "movie_name": "Splash (1984)", "rating": 4}, "179": {"movie_id": 1380, "timestamp": 1015018465, "Genre": "Comedy|Musical|Romance", "movie_name": "Grease (1978)", "rating": 3}, "180": {"movie_id": 861, "timestamp": 969811443, "Genre": "Action|Thriller", "movie_name": "Supercop (1992)", "rating": 3}, "181": {"movie_id": 1997, "timestamp": 976308131, "Genre": "Horror", "movie_name": "Exorcist, The (1973)", "rating": 4}, "182": {"movie_id": 474, "timestamp": 969811365, "Genre": "Action|Thriller", "movie_name": "In the Line of Fire (1993)", "rating": 4}, "183": {"movie_id": 1221, "timestamp": 976306369, "Genre": "Action|Crime|Drama", "movie_name": "Godfather: Part II, The (1974)", "rating": 5}, "184": {"movie_id": 2336, "timestamp": 969810990, "Genre": "Drama", "movie_name": "Elizabeth (1998)", "rating": 4}, "185": {"movie_id": 1682, "timestamp": 969810942, "Genre": "Drama", "movie_name": "Truman Show, The (1998)", "rating": 4}, "186": {"movie_id": 1476, "timestamp": 969809844, "Genre": "Comedy|Drama", "movie_name": "Private Parts (1997)", "rating": 3}, "187": {"movie_id": 58, "timestamp": 969811533, "Genre": "Drama|Romance", "movie_name": "Postino, Il (The Postman) (1994)", "rating": 5}, "188": {"movie_id": 2712, "timestamp": 969811401, "Genre": "Drama", "movie_name": "Eyes Wide Shut (1999)", "rating": 4}, "189": {"movie_id": 1916, "timestamp": 969809936, "Genre": "Action|Comedy|Drama", "movie_name": "Buffalo 66 (1998)", "rating": 4}, "190": {"movie_id": 1120, "timestamp": 969811475, "Genre": "Drama", "movie_name": "People vs. Larry Flynt, The (1996)", "rating": 4}, "191": {"movie_id": 1639, "timestamp": 1018893191, "Genre": "Drama|Romance", "movie_name": "Chasing Amy (1997)", "rating": 2}, "192": {"movie_id": 1711, "timestamp": 969810091, "Genre": "Comedy|Crime|Drama|Mystery", "movie_name": "Midnight in the Garden of Good and Evil (1997)", "rating": 2}, "193": {"movie_id": 538, "timestamp": 969811155, "Genre": "Drama", "movie_name": "Six Degrees of Separation (1993)", "rating": 4}, "194": {"movie_id": 393, "timestamp": 976303081, "Genre": "Action", "movie_name": "Street Fighter (1994)", "rating": 3}, "195": {"movie_id": 111, "timestamp": 1011373692, "Genre": "Drama|Thriller", "movie_name": "Taxi Driver (1976)", "rating": 5}, "196": {"movie_id": 1589, "timestamp": 969811600, "Genre": "Crime|Drama|Mystery", "movie_name": "Cop Land (1997)", "rating": 4}, "197": {"movie_id": 337, "timestamp": 969811100, "Genre": "Drama", "movie_name": "What's Eating Gilbert Grape (1993)", "rating": 4}, "198": {"movie_id": 555, "timestamp": 969811301, "Genre": "Action|Crime|Romance", "movie_name": "True Romance (1993)", "rating": 5}, "199": {"movie_id": 3481, "timestamp": 969809106, "Genre": "Comedy", "movie_name": "High Fidelity (2000)", "rating": 5}, "200": {"movie_id": 345, "timestamp": 1015018190, "Genre": "Comedy|Drama", "movie_name": "Adventures of Priscilla, Queen of the Desert, The (1994)", "rating": 2}, "201": {"movie_id": 25, "timestamp": 969810967, "Genre": "Drama|Romance", "movie_name": "Leaving Las Vegas (1995)", "rating": 3}, "202": {"movie_id": 2329, "timestamp": 1018892317, "Genre": "Drama", "movie_name": "American History X (1998)", "rating": 5}, "203": {"movie_id": 1673, "timestamp": 969811237, "Genre": "Drama", "movie_name": "Boogie Nights (1997)", "rating": 4}, "204": {"movie_id": 367, "timestamp": 1015019004, "Genre": "Comedy|Crime|Fantasy", "movie_name": "Mask, The (1994)", "rating": 3}, "205": {"movie_id": 223, "timestamp": 969811100, "Genre": "Comedy", "movie_name": "Clerks (1994)", "rating": 3}, "206": {"movie_id": 3948, "timestamp": 1008795018, "Genre": "Comedy", "movie_name": "Meet the Parents (2000)", "rating": 5}, "207": {"movie_id": 1777, "timestamp": 969809936, "Genre": "Comedy|Romance", "movie_name": "Wedding Singer, The (1998)", "rating": 2}, "208": {"movie_id": 1343, "timestamp": 969811132, "Genre": "Thriller", "movie_name": "Cape Fear (1991)", "rating": 3}, "209": {"movie_id": 3160, "timestamp": 969809106, "Genre": "Drama", "movie_name": "Magnolia (1999)", "rating": 3}, "210": {"movie_id": 529, "timestamp": 969810990, "Genre": "Drama", "movie_name": "Searching for Bobby Fischer (1993)", "rating": 5}, "211": {"movie_id": 1060, "timestamp": 969810967, "Genre": "Comedy|Drama", "movie_name": "Swingers (1996)", "rating": 5}, "212": {"movie_id": 3751, "timestamp": 1008794761, "Genre": "Animation|Children's|Comedy", "movie_name": "Chicken Run (2000)", "rating": 4}, "213": {"movie_id": 2302, "timestamp": 969812502, "Genre": "Comedy", "movie_name": "My Cousin Vinny (1992)", "rating": 4}, "214": {"movie_id": 1148, "timestamp": 969809357, "Genre": "Animation|Comedy", "movie_name": "Wrong Trousers, The (1993)", "rating": 5}, "215": {"movie_id": 3253, "timestamp": 969809781, "Genre": "Comedy", "movie_name": "Wayne's World (1992)", "rating": 5}, "216": {"movie_id": 1584, "timestamp": 969811426, "Genre": "Drama|Sci-Fi", "movie_name": "Contact (1997)", "rating": 2}, "217": {"movie_id": 1223, "timestamp": 969810783, "Genre": "Animation|Comedy", "movie_name": "Grand Day Out, A (1992)", "rating": 5}, "218": {"movie_id": 778, "timestamp": 969810860, "Genre": "Drama", "movie_name": "Trainspotting (1996)", "rating": 5}, "219": {"movie_id": 1307, "timestamp": 969812232, "Genre": "Comedy|Romance", "movie_name": "When Harry Met Sally... (1989)", "rating": 5}, "220": {"movie_id": 3270, "timestamp": 976308172, "Genre": "Drama", "movie_name": "Cutting Edge, The (1992)", "rating": 4}, "221": {"movie_id": 1310, "timestamp": 1018715479, "Genre": "Documentary", "movie_name": "Hype! (1996)", "rating": 3}, "222": {"movie_id": 428, "timestamp": 969811381, "Genre": "Drama", "movie_name": "Bronx Tale, A (1993)", "rating": 4}, "223": {"movie_id": 2124, "timestamp": 969809844, "Genre": "Comedy", "movie_name": "Addams Family, The (1991)", "rating": 4}, "224": {"movie_id": 2054, "timestamp": 1015019241, "Genre": "Adventure|Children's|Comedy|Fantasy|Sci-Fi", "movie_name": "Honey, I Shrunk the Kids (1989)", "rating": 2}, "225": {"movie_id": 1252, "timestamp": 972685437, "Genre": "Film-Noir|Mystery|Thriller", "movie_name": "Chinatown (1974)", "rating": 5}, "226": {"movie_id": 3869, "timestamp": 969808880, "Genre": "Comedy", "movie_name": "Naked Gun 2 1/2: The Smell of Fear, The (1991)", "rating": 2}, "227": {"movie_id": 1256, "timestamp": 976303771, "Genre": "Comedy|War", "movie_name": "Duck Soup (1933)", "rating": 4}, "228": {"movie_id": 3363, "timestamp": 969812188, "Genre": "Comedy|Drama", "movie_name": "American Graffiti (1973)", "rating": 3}, "229": {"movie_id": 586, "timestamp": 969810401, "Genre": "Children's|Comedy", "movie_name": "Home Alone (1990)", "rating": 1}, "230": {"movie_id": 587, "timestamp": 969810190, "Genre": "Comedy|Romance|Thriller", "movie_name": "Ghost (1990)", "rating": 3}, "231": {"movie_id": 2, "timestamp": 976302794, "Genre": "Adventure|Children's|Fantasy", "movie_name": "Jumanji (1995)", "rating": 2}, "232": {"movie_id": 2133, "timestamp": 1015018915, "Genre": "Adventure|Comedy", "movie_name": "Adventures in Babysitting (1987)", "rating": 2}, "233": {"movie_id": 2136, "timestamp": 969808940, "Genre": "Comedy", "movie_name": "Nutty Professor, The (1963)", "rating": 3}, "234": {"movie_id": 1918, "timestamp": 969810422, "Genre": "Action|Comedy|Crime|Drama", "movie_name": "Lethal Weapon 4 (1998)", "rating": 2}, "235": {"movie_id": 1271, "timestamp": 969811583, "Genre": "Drama", "movie_name": "Fried Green Tomatoes (1991)", "rating": 4}, "236": {"movie_id": 2078, "timestamp": 969812381, "Genre": "Animation|Children's|Comedy|Musical", "movie_name": "Jungle Book, The (1967)", "rating": 5}, "237": {"movie_id": 1276, "timestamp": 969811813, "Genre": "Comedy|Drama", "movie_name": "Cool Hand Luke (1967)", "rating": 5}, "238": {"movie_id": 671, "timestamp": 969810002, "Genre": "Comedy|Sci-Fi", "movie_name": "Mystery Science Theater 3000: The Movie (1996)", "rating": 4}, "239": {"movie_id": 1278, "timestamp": 969811879, "Genre": "Comedy|Horror", "movie_name": "Young Frankenstein (1974)", "rating": 5}, "240": {"movie_id": 2657, "timestamp": 969812350, "Genre": "Comedy|Horror|Musical|Sci-Fi", "movie_name": "Rocky Horror Picture Show, The (1975)", "rating": 5}, "241": {"movie_id": 3388, "timestamp": 1015019399, "Genre": "Comedy", "movie_name": "Harry and the Hendersons (1987)", "rating": 2}, "242": {"movie_id": 2080, "timestamp": 969812350, "Genre": "Animation|Children's|Comedy|Musical|Romance", "movie_name": "Lady and the Tramp (1955)", "rating": 5}, "243": {"movie_id": 1282, "timestamp": 1015019642, "Genre": "Animation|Children's|Musical", "movie_name": "Fantasia (1940)", "rating": 4}, "244": {"movie_id": 750, "timestamp": 976303771, "Genre": "Sci-Fi|War", "movie_name": "Dr. Strangelove or: How I Learned to Stop Worrying and Love the Bomb (1963)", "rating": 5}, "245": {"movie_id": 2087, "timestamp": 976302689, "Genre": "Animation|Children's|Fantasy|Musical", "movie_name": "Peter Pan (1953)", "rating": 4}, "246": {"movie_id": 3608, "timestamp": 969812288, "Genre": "Comedy", "movie_name": "Pee-wee's Big Adventure (1985)", "rating": 5}, "247": {"movie_id": 2300, "timestamp": 969811961, "Genre": "Comedy|Musical", "movie_name": "Producers, The (1968)", "rating": 4}, "248": {"movie_id": 180, "timestamp": 969809780, "Genre": "Comedy", "movie_name": "Mallrats (1995)", "rating": 3}, "249": {"movie_id": 3037, "timestamp": 969811961, "Genre": "Comedy|Drama|Western", "movie_name": "Little Big Man (1970)", "rating": 4}, "250": {"movie_id": 3039, "timestamp": 969812311, "Genre": "Comedy", "movie_name": "Trading Places (1983)", "rating": 5}, "251": {"movie_id": 904, "timestamp": 976306436, "Genre": "Mystery|Thriller", "movie_name": "Rear Window (1954)", "rating": 5}, "252": {"movie_id": 1292, "timestamp": 969811842, "Genre": "Comedy", "movie_name": "Being There (1979)", "rating": 5}, "253": {"movie_id": 2746, "timestamp": 969812542, "Genre": "Comedy|Horror|Musical", "movie_name": "Little Shop of Horrors (1986)", "rating": 4}, "254": {"movie_id": 1009, "timestamp": 976302776, "Genre": "Adventure|Children's|Fantasy", "movie_name": "Escape to Witch Mountain (1975)", "rating": 4}, "255": {"movie_id": 333, "timestamp": 969810376, "Genre": "Comedy", "movie_name": "Tommy Boy (1995)", "rating": 5}, "256": {"movie_id": 2174, "timestamp": 969812120, "Genre": "Comedy|Fantasy", "movie_name": "Beetlejuice (1988)", "rating": 5}, "257": {"movie_id": 1377, "timestamp": 969810070, "Genre": "Action|Adventure|Comedy|Crime", "movie_name": "Batman Returns (1992)", "rating": 3}, "258": {"movie_id": 3629, "timestamp": 969812232, "Genre": "Comedy", "movie_name": "Gold Rush, The (1925)", "rating": 5}, "259": {"movie_id": 344, "timestamp": 969810150, "Genre": "Comedy", "movie_name": "Ace Ventura: Pet Detective (1994)", "rating": 5}, "260": {"movie_id": 923, "timestamp": 972685437, "Genre": "Drama", "movie_name": "Citizen Kane (1941)", "rating": 5}, "261": {"movie_id": 858, "timestamp": 972685437, "Genre": "Action|Crime|Drama", "movie_name": "Godfather, The (1972)", "rating": 5}, "262": {"movie_id": 1967, "timestamp": 976302755, "Genre": "Adventure|Children's|Fantasy", "movie_name": "Labyrinth (1986)", "rating": 4}, "263": {"movie_id": 2405, "timestamp": 1015019559, "Genre": "Action|Adventure|Comedy|Romance", "movie_name": "Jewel of the Nile, The (1985)", "rating": 3}, "264": {"movie_id": 1104, "timestamp": 976303836, "Genre": "Drama", "movie_name": "Streetcar Named Desire, A (1951)", "rating": 5}, "265": {"movie_id": 435, "timestamp": 1015019481, "Genre": "Comedy|Sci-Fi", "movie_name": "Coneheads (1993)", "rating": 2}, "266": {"movie_id": 1042, "timestamp": 969812441, "Genre": "Comedy", "movie_name": "That Thing You Do! (1996)", "rating": 3}, "267": {"movie_id": 2423, "timestamp": 1015018592, "Genre": "Comedy", "movie_name": "Christmas Vacation (1989)", "rating": 2}, "268": {"movie_id": 2424, "timestamp": 1015019112, "Genre": "Comedy|Romance", "movie_name": "You've Got Mail (1998)", "rating": 1}, "269": {"movie_id": 3087, "timestamp": 1015018750, "Genre": "Comedy", "movie_name": "Scrooged (1988)", "rating": 4}, "270": {"movie_id": 953, "timestamp": 976308203, "Genre": "Drama", "movie_name": "It's a Wonderful Life (1946)", "rating": 4}, "271": {"movie_id": 1125, "timestamp": 969812441, "Genre": "Comedy", "movie_name": "Return of the Pink Panther, The (1974)", "rating": 5}, "272": {"movie_id": 2795, "timestamp": 969812232, "Genre": "Comedy", "movie_name": "Vacation (1983)", "rating": 5}, "273": {"movie_id": 2000, "timestamp": 969812350, "Genre": "Action|Comedy|Crime|Drama", "movie_name": "Lethal Weapon (1987)", "rating": 5}, "274": {"movie_id": 2001, "timestamp": 1015018445, "Genre": "Action|Comedy|Crime|Drama", "movie_name": "Lethal Weapon 2 (1989)", "rating": 3}, "275": {"movie_id": 2003, "timestamp": 969812542, "Genre": "Comedy|Horror", "movie_name": "Gremlins (1984)", "rating": 3}, "276": {"movie_id": 2005, "timestamp": 976302755, "Genre": "Adventure|Children's|Fantasy", "movie_name": "Goonies, The (1985)", "rating": 3}, "277": {"movie_id": 969, "timestamp": 976307058, "Genre": "Action|Adventure|Romance|War", "movie_name": "African Queen, The (1951)", "rating": 5}, "278": {"movie_id": 539, "timestamp": 969810283, "Genre": "Comedy|Romance", "movie_name": "Sleepless in Seattle (1993)", "rating": 3}, "279": {"movie_id": 2371, "timestamp": 969812560, "Genre": "Comedy", "movie_name": "Fletch (1985)", "rating": 5}, "280": {"movie_id": 3247, "timestamp": 969810422, "Genre": "Comedy|Crime", "movie_name": "Sister Act (1992)", "rating": 1}, "281": {"movie_id": 971, "timestamp": 976307816, "Genre": "Drama", "movie_name": "Cat on a Hot Tin Roof (1958)", "rating": 5}, "282": {"movie_id": 2011, "timestamp": 969812560, "Genre": "Comedy|Sci-Fi", "movie_name": "Back to the Future Part II (1989)", "rating": 2}, "283": {"movie_id": 2012, "timestamp": 969810190, "Genre": "Comedy|Sci-Fi|Western", "movie_name": "Back to the Future Part III (1990)", "rating": 2}, "284": {"movie_id": 2015, "timestamp": 976302755, "Genre": "Children's|Comedy|Fantasy", "movie_name": "Absent Minded Professor, The (1961)", "rating": 4}, "285": {"movie_id": 1215, "timestamp": 969809715, "Genre": "Action|Adventure|Comedy|Horror|Sci-Fi", "movie_name": "Army of Darkness (1993)", "rating": 5}, "286": {"movie_id": 1073, "timestamp": 976302689, "Genre": "Adventure|Children's|Comedy|Fantasy", "movie_name": "Willy Wonka and the Chocolate Factory (1971)", "rating": 5}, "287": {"movie_id": 541, "timestamp": 976302409, "Genre": "Film-Noir|Sci-Fi", "movie_name": "Blade Runner (1982)", "rating": 5}, "288": {"movie_id": 543, "timestamp": 969809936, "Genre": "Comedy|Romance|Thriller", "movie_name": "So I Married an Axe Murderer (1993)", "rating": 4}, "289": {"movie_id": 3254, "timestamp": 969810222, "Genre": "Comedy", "movie_name": "Wayne's World 2 (1993)", "rating": 3}, "290": {"movie_id": 1220, "timestamp": 969811961, "Genre": "Action|Comedy|Musical", "movie_name": "Blues Brothers, The (1980)", "rating": 5}, "291": {"movie_id": 1080, "timestamp": 969811842, "Genre": "Comedy", "movie_name": "Monty Python's Life of Brian (1979)", "rating": 5}, "292": {"movie_id": 2968, "timestamp": 976302689, "Genre": "Adventure|Fantasy|Sci-Fi", "movie_name": "Time Bandits (1981)", "rating": 4}, "293": {"movie_id": 3264, "timestamp": 1015018854, "Genre": "Comedy|Horror", "movie_name": "Buffy the Vampire Slayer (1992)", "rating": 4}, "294": {"movie_id": 3198, "timestamp": 1011373300, "Genre": "Drama", "movie_name": "Papillon (1973)", "rating": 5}, "295": {"movie_id": 1230, "timestamp": 969811813, "Genre": "Comedy|Romance", "movie_name": "Annie Hall (1977)", "rating": 5}, "296": {"movie_id": 2108, "timestamp": 969809748, "Genre": "Comedy|Romance", "movie_name": "L.A. Story (1991)", "rating": 3}, "297": {"movie_id": 1234, "timestamp": 969811879, "Genre": "Comedy|Crime", "movie_name": "Sting, The (1973)", "rating": 5}, "298": {"movie_id": 2109, "timestamp": 969812188, "Genre": "Comedy", "movie_name": "Jerk, The (1979)", "rating": 5}, "299": {"movie_id": 203, "timestamp": 969810456, "Genre": "Comedy", "movie_name": "To Wong Foo, Thanks for Everything! Julie Newmar (1995)", "rating": 2}, "300": {"movie_id": 1676, "timestamp": 969811646, "Genre": "Action|Adventure|Sci-Fi|War", "movie_name": "Starship Troopers (1997)", "rating": 5}, "301": {"movie_id": 2111, "timestamp": 969812606, "Genre": "Comedy", "movie_name": "Man with Two Brains, The (1983)", "rating": 5}, "302": {"movie_id": 216, "timestamp": 969810401, "Genre": "Comedy", "movie_name": "Billy Madison (1995)", "rating": 5}, "303": {"movie_id": 663, "timestamp": 969809978, "Genre": "Comedy", "movie_name": "Kids in the Hall: Brain Candy (1996)", "rating": 4}, "304": {"movie_id": 3448, "timestamp": 969812522, "Genre": "Comedy|Drama|War", "movie_name": "Good Morning, Vietnam (1987)", "rating": 4}, "305": {"movie_id": 231, "timestamp": 1015018728, "Genre": "Comedy", "movie_name": "Dumb & Dumber (1994)", "rating": 4}, "306": {"movie_id": 2076, "timestamp": 976307655, "Genre": "Drama|Mystery", "movie_name": "Blue Velvet (1986)", "rating": 5}, "307": {"movie_id": 246, "timestamp": 969810783, "Genre": "Documentary", "movie_name": "Hoop Dreams (1994)", "rating": 5}, "308": {"movie_id": 1288, "timestamp": 969811915, "Genre": "Comedy|Drama|Musical", "movie_name": "This Is Spinal Tap (1984)", "rating": 5}, "309": {"movie_id": 3396, "timestamp": 969812032, "Genre": "Children's|Comedy", "movie_name": "Muppet Movie, The (1979)", "rating": 4}, "310": {"movie_id": 342, "timestamp": 969812486, "Genre": "Comedy|Romance", "movie_name": "Muriel's Wedding (1994)", "rating": 4}, "311": {"movie_id": 788, "timestamp": 969810283, "Genre": "Comedy|Fantasy|Romance|Sci-Fi", "movie_name": "Nutty Professor, The (1996)", "rating": 3}, "312": {"movie_id": 1546, "timestamp": 976301973, "Genre": "Comedy", "movie_name": "Schizopolis (1996)", "rating": 4}, "313": {"movie_id": 440, "timestamp": 1015017729, "Genre": "Comedy|Romance", "movie_name": "Dave (1993)", "rating": 1}, "314": {"movie_id": 441, "timestamp": 969809629, "Genre": "Comedy", "movie_name": "Dazed and Confused (1993)", "rating": 5}, "315": {"movie_id": 85, "timestamp": 969811195, "Genre": "Drama|Romance", "movie_name": "Angels and Insects (1995)", "rating": 3}, "316": {"movie_id": 708, "timestamp": 1015018421, "Genre": "Comedy|Romance", "movie_name": "Truth About Cats & Dogs, The (1996)", "rating": 3}, "317": {"movie_id": 3897, "timestamp": 1008794502, "Genre": "Comedy|Drama", "movie_name": "Almost Famous (2000)", "rating": 4}, "318": {"movie_id": 999, "timestamp": 969811646, "Genre": "Crime", "movie_name": "2 Days in the Valley (1996)", "rating": 3}, "319": {"movie_id": 1262, "timestamp": 976307325, "Genre": "Adventure|War", "movie_name": "Great Escape, The (1963)", "rating": 5}, "320": {"movie_id": 3070, "timestamp": 1015019151, "Genre": "Adventure|Comedy|Sci-Fi", "movie_name": "Adventures of Buckaroo Bonzai Across the 8th Dimension, The (1984)", "rating": 3}, "321": {"movie_id": 1263, "timestamp": 976308131, "Genre": "Drama|War", "movie_name": "Deer Hunter, The (1978)", "rating": 5}, "322": {"movie_id": 2731, "timestamp": 976303836, "Genre": "Drama", "movie_name": "400 Blows, The (Les Quatre cents coups) (1959)", "rating": 5}, "323": {"movie_id": 2243, "timestamp": 969812453, "Genre": "Comedy|Drama|Romance", "movie_name": "Broadcast News (1987)", "rating": 3}, "324": {"movie_id": 2567, "timestamp": 969810244, "Genre": "Comedy", "movie_name": "EDtv (1999)", "rating": 4}, "325": {"movie_id": 1783, "timestamp": 976302566, "Genre": "Film-Noir|Mystery|Thriller", "movie_name": "Palmetto (1998)", "rating": 3}, "326": {"movie_id": 3535, "timestamp": 1008795207, "Genre": "Comedy|Horror|Thriller", "movie_name": "American Psycho (2000)", "rating": 1}, "327": {"movie_id": 1883, "timestamp": 969811321, "Genre": "Comedy", "movie_name": "Bulworth (1998)", "rating": 4}, "328": {"movie_id": 1396, "timestamp": 969811264, "Genre": "Crime|Drama|Sci-Fi", "movie_name": "Sneakers (1992)", "rating": 3}, "329": {"movie_id": 500, "timestamp": 969810244, "Genre": "Comedy", "movie_name": "Mrs. Doubtfire (1993)", "rating": 1}, "330": {"movie_id": 70, "timestamp": 969810190, "Genre": "Action|Comedy|Crime|Horror|Thriller", "movie_name": "From Dusk Till Dawn (1996)", "rating": 4}, "331": {"movie_id": 2387, "timestamp": 1015019269, "Genre": "Comedy|Crime", "movie_name": "Very Bad Things (1998)", "rating": 2}, "332": {"movie_id": 553, "timestamp": 969811210, "Genre": "Western", "movie_name": "Tombstone (1993)", "rating": 4}, "333": {"movie_id": 3261, "timestamp": 969809964, "Genre": "Comedy|Drama|Romance", "movie_name": "Singles (1992)", "rating": 3}, "334": {"movie_id": 1805, "timestamp": 969811512, "Genre": "Crime|Drama|Mystery|Thriller", "movie_name": "Wild Things (1998)", "rating": 4}, "335": {"movie_id": 3773, "timestamp": 969810542, "Genre": "Comedy", "movie_name": "House Party (1990)", "rating": 3}, "336": {"movie_id": 2369, "timestamp": 1015019135, "Genre": "Comedy|Romance", "movie_name": "Desperately Seeking Susan (1985)", "rating": 4}, "337": {"movie_id": 1179, "timestamp": 969811042, "Genre": "Crime|Drama|Film-Noir", "movie_name": "Grifters, The (1990)", "rating": 5}, "338": {"movie_id": 319, "timestamp": 969811301, "Genre": "Thriller", "movie_name": "Shallow Grave (1994)", "rating": 4}, "339": {"movie_id": 247, "timestamp": 1018892637, "Genre": "Drama|Fantasy|Romance|Thriller", "movie_name": "Heavenly Creatures (1994)", "rating": 5}, "340": {"movie_id": 1428, "timestamp": 1011372072, "Genre": "Drama", "movie_name": "Angel Baby (1995)", "rating": 3}, "341": {"movie_id": 1284, "timestamp": 976302319, "Genre": "Film-Noir|Mystery", "movie_name": "Big Sleep, The (1946)", "rating": 5}, "342": {"movie_id": 2912, "timestamp": 969810942, "Genre": "Action|Crime|Drama", "movie_name": "Limey, The (1999)", "rating": 4}, "343": {"movie_id": 293, "timestamp": 969810885, "Genre": "Crime|Drama|Romance|Thriller", "movie_name": "Professional, The (a.k.a. Leon: The Professional) (1994)", "rating": 5}, "344": {"movie_id": 1614, "timestamp": 969810283, "Genre": "Comedy", "movie_name": "In & Out (1997)", "rating": 1}, "345": {"movie_id": 1206, "timestamp": 976307344, "Genre": "Sci-Fi", "movie_name": "Clockwork Orange, A (1971)", "rating": 5}, "346": {"movie_id": 707, "timestamp": 976302566, "Genre": "Crime|Film-Noir|Thriller", "movie_name": "Mulholland Falls (1996)", "rating": 2}, "347": {"movie_id": 2542, "timestamp": 969811195, "Genre": "Comedy|Crime|Thriller", "movie_name": "Lock, Stock & Two Smoking Barrels (1998)", "rating": 3}, "348": {"movie_id": 496, "timestamp": 1044314906, "Genre": "Comedy|Drama|Romance", "movie_name": "What Happened Was... (1994)", "rating": 5}, "349": {"movie_id": 1748, "timestamp": 1008795594, "Genre": "Film-Noir|Sci-Fi|Thriller", "movie_name": "Dark City (1998)", "rating": 4}, "350": {"movie_id": 2145, "timestamp": 1015018961, "Genre": "Comedy|Drama|Romance", "movie_name": "Pretty in Pink (1986)", "rating": 3}, "351": {"movie_id": 1344, "timestamp": 976302495, "Genre": "Film-Noir|Thriller", "movie_name": "Cape Fear (1962)", "rating": 4}, "352": {"movie_id": 3526, "timestamp": 969812441, "Genre": "Comedy|Drama", "movie_name": "Parenthood (1989)", "rating": 5}, "353": {"movie_id": 2248, "timestamp": 969811915, "Genre": "Comedy|Drama|Romance", "movie_name": "Say Anything... (1989)", "rating": 5}, "354": {"movie_id": 1391, "timestamp": 969810168, "Genre": "Action|Comedy|Sci-Fi|War", "movie_name": "Mars Attacks! (1996)", "rating": 2}, "355": {"movie_id": 532, "timestamp": 969810205, "Genre": "Comedy|Crime|Horror", "movie_name": "Serial Mom (1994)", "rating": 3}, "356": {"movie_id": 466, "timestamp": 969810337, "Genre": "Action|Comedy|War", "movie_name": "Hot Shots! Part Deux (1993)", "rating": 3}, "357": {"movie_id": 2014, "timestamp": 1015019399, "Genre": "Children's|Comedy", "movie_name": "Freaky Friday (1977)", "rating": 4}, "358": {"movie_id": 2025, "timestamp": 969811583, "Genre": "Drama|Romance", "movie_name": "Lolita (1997)", "rating": 4}, "359": {"movie_id": 3911, "timestamp": 972685524, "Genre": "Comedy", "movie_name": "Best in Show (2000)", "rating": 4}, "360": {"movie_id": 1094, "timestamp": 969811564, "Genre": "Drama|Romance|War", "movie_name": "Crying Game, The (1992)", "rating": 4}, "361": {"movie_id": 1258, "timestamp": 976308172, "Genre": "Horror", "movie_name": "Shining, The (1980)", "rating": 5}, "362": {"movie_id": 1407, "timestamp": 969811132, "Genre": "Horror|Thriller", "movie_name": "Scream (1996)", "rating": 4}, "363": {"movie_id": 2064, "timestamp": 969812158, "Genre": "Comedy|Documentary", "movie_name": "Roger & Me (1989)", "rating": 5}, "364": {"movie_id": 2160, "timestamp": 976308172, "Genre": "Horror|Thriller", "movie_name": "Rosemary's Baby (1968)", "rating": 5}, "365": {"movie_id": 785, "timestamp": 969809964, "Genre": "Comedy", "movie_name": "Kingpin (1996)", "rating": 4}, "366": {"movie_id": 2195, "timestamp": 969810422, "Genre": "Comedy", "movie_name": "Dirty Work (1998)", "rating": 1}, "367": {"movie_id": 2502, "timestamp": 1015017410, "Genre": "Comedy|Romance", "movie_name": "Office Space (1999)", "rating": 5}, "368": {"movie_id": 1219, "timestamp": 976306894, "Genre": "Horror|Thriller", "movie_name": "Psycho (1960)", "rating": 5}, "369": {"movie_id": 585, "timestamp": 969809936, "Genre": "Comedy", "movie_name": "Brady Bunch Movie, The (1995)", "rating": 3}, "370": {"movie_id": 2134, "timestamp": 1015018986, "Genre": "Comedy", "movie_name": "Weird Science (1985)", "rating": 4}, "371": {"movie_id": 818, "timestamp": 1015019577, "Genre": "Comedy", "movie_name": "Very Brady Sequel, A (1996)", "rating": 3}, "372": {"movie_id": 3450, "timestamp": 969810091, "Genre": "Comedy", "movie_name": "Grumpy Old Men (1993)", "rating": 3}, "373": {"movie_id": 312, "timestamp": 969810301, "Genre": "Comedy", "movie_name": "Stuart Saves His Family (1995)", "rating": 3}, "374": {"movie_id": 2150, "timestamp": 969812469, "Genre": "Comedy", "movie_name": "Gods Must Be Crazy, The (1980)", "rating": 4}, "375": {"movie_id": 910, "timestamp": 969812092, "Genre": "Comedy|Crime", "movie_name": "Some Like It Hot (1959)", "rating": 5}, "376": {"movie_id": 2249, "timestamp": 969810456, "Genre": "Comedy", "movie_name": "My Blue Heaven (1990)", "rating": 1}, "377": {"movie_id": 3052, "timestamp": 969809629, "Genre": "Comedy", "movie_name": "Dogma (1999)", "rating": 3}, "378": {"movie_id": 429, "timestamp": 969810498, "Genre": "Comedy", "movie_name": "Cabin Boy (1994)", "rating": 5}, "379": {"movie_id": 3210, "timestamp": 969812311, "Genre": "Comedy", "movie_name": "Fast Times at Ridgemont High (1982)", "rating": 5}, "380": {"movie_id": 2416, "timestamp": 1015019189, "Genre": "Comedy", "movie_name": "Back to School (1986)", "rating": 3}, "381": {"movie_id": 3243, "timestamp": 969810456, "Genre": "Comedy", "movie_name": "Encino Man (1992)", "rating": 3}, "382": {"movie_id": 3258, "timestamp": 969810337, "Genre": "Comedy", "movie_name": "Death Becomes Her (1992)", "rating": 3}, "383": {"movie_id": 112, "timestamp": 969811426, "Genre": "Action|Adventure|Crime", "movie_name": "Rumble in the Bronx (1995)", "rating": 3}, "384": {"movie_id": 1249, "timestamp": 969810885, "Genre": "Thriller", "movie_name": "Nikita (La Femme Nikita) (1990)", "rating": 4}, "385": {"movie_id": 3435, "timestamp": 976302319, "Genre": "Crime|Film-Noir", "movie_name": "Double Indemnity (1944)", "rating": 5}, "386": {"movie_id": 1267, "timestamp": 976302319, "Genre": "Film-Noir|Thriller", "movie_name": "Manchurian Candidate, The (1962)", "rating": 5}, "387": {"movie_id": 1199, "timestamp": 976308152, "Genre": "Sci-Fi", "movie_name": "Brazil (1985)", "rating": 5}, "388": {"movie_id": 3521, "timestamp": 969812120, "Genre": "Comedy|Crime|Drama", "movie_name": "Mystery Train (1989)", "rating": 5}, "389": {"movie_id": 2726, "timestamp": 976302409, "Genre": "Crime|Film-Noir", "movie_name": "Killing, The (1956)", "rating": 4}, "390": {"movie_id": 3104, "timestamp": 1015017410, "Genre": "Action|Adventure|Comedy|Crime", "movie_name": "Midnight Run (1988)", "rating": 5}, "391": {"movie_id": 187, "timestamp": 969810002, "Genre": "Comedy", "movie_name": "Party Girl (1995)", "rating": 3}, "392": {"movie_id": 903, "timestamp": 976307103, "Genre": "Mystery|Thriller", "movie_name": "Vertigo (1958)", "rating": 5}, "393": {"movie_id": 3551, "timestamp": 1011373692, "Genre": "Thriller", "movie_name": "Marathon Man (1976)", "rating": 4}, "394": {"movie_id": 1958, "timestamp": 1015017083, "Genre": "Comedy|Drama", "movie_name": "Terms of Endearment (1983)", "rating": 3}, "395": {"movie_id": 1965, "timestamp": 969812120, "Genre": "Comedy|Sci-Fi", "movie_name": "Repo Man (1984)", "rating": 5}, "396": {"movie_id": 45, "timestamp": 969809844, "Genre": "Comedy|Drama", "movie_name": "To Die For (1995)", "rating": 4}, "397": {"movie_id": 3741, "timestamp": 976303707, "Genre": "Crime|Drama", "movie_name": "Badlands (1973)", "rating": 4}, "398": {"movie_id": 1212, "timestamp": 976306652, "Genre": "Mystery|Thriller", "movie_name": "Third Man, The (1949)", "rating": 5}, "399": {"movie_id": 125, "timestamp": 969809715, "Genre": "Comedy", "movie_name": "Flirting With Disaster (1996)", "rating": 5}, "400": {"movie_id": 2973, "timestamp": 976301821, "Genre": "Comedy", "movie_name": "Crimes and Misdemeanors (1989)", "rating": 4}, "401": {"movie_id": 3424, "timestamp": 976301511, "Genre": "Comedy|Drama", "movie_name": "Do the Right Thing (1989)", "rating": 4}, "402": {"movie_id": 3361, "timestamp": 969812032, "Genre": "Comedy", "movie_name": "Bull Durham (1988)", "rating": 5}, "403": {"movie_id": 2132, "timestamp": 976307180, "Genre": "Drama", "movie_name": "Who's Afraid of Virginia Woolf? (1966)", "rating": 5}, "404": {"movie_id": 2144, "timestamp": 969812381, "Genre": "Comedy", "movie_name": "Sixteen Candles (1984)", "rating": 5}, "405": {"movie_id": 2245, "timestamp": 1015019044, "Genre": "Comedy|Drama", "movie_name": "Working Girl (1988)", "rating": 3}, "406": {"movie_id": 2915, "timestamp": 969812417, "Genre": "Comedy", "movie_name": "Risky Business (1983)", "rating": 5}, "407": {"movie_id": 372, "timestamp": 969810244, "Genre": "Comedy|Drama", "movie_name": "Reality Bites (1994)", "rating": 3}, "408": {"movie_id": 2352, "timestamp": 969812288, "Genre": "Comedy|Drama", "movie_name": "Big Chill, The (1983)", "rating": 4}, "409": {"movie_id": 1663, "timestamp": 969812261, "Genre": "Comedy", "movie_name": "Stripes (1981)", "rating": 5}, "410": {"movie_id": 157, "timestamp": 1015019325, "Genre": "Comedy|War", "movie_name": "Canadian Bacon (1994)", "rating": 3}, "411": {"movie_id": 3676, "timestamp": 1011373829, "Genre": "Drama|Horror", "movie_name": "Eraserhead (1977)", "rating": 5}, "412": {"movie_id": 3422, "timestamp": 1015018554, "Genre": "Comedy|Romance", "movie_name": "She's Gotta Have It (1986)", "rating": 4}}}}